[
    {
        "titulo": "InShot",
        "servidor": "Servidor Oficial Rapido (Internet Archive)",
        "tag": "Edicion",
        "status": "Pro",
        "peso": "  75.3 mb",
        "imagen": "https://i.postimg.cc/xdVBYhWj/image.png"
    },
    {
        "titulo": "Dismplusplus",
        "servidor": "Servidor Oficial Rápido (Internet Archive)",
        "tag": "Windows",
        "status": "Rendimiento",
        "peso": "  3.3 mb",
        "imagen": "https://i.postimg.cc/pLVyXc83/image.png"
    }
    
]

